nabeelxd/__init__.py
nabeelxd/core.py
nabeelxd-0.1.1.dist-info/METADATA
nabeelxd-0.1.1.dist-info/WHEEL
nabeelxd-0.1.1.dist-info/top_level.txt
nabeelxd-0.1.1.dist-info/RECORD
