Metadata-Version: 2.4
Name: nabeelxd
Version: 0.1.1
Summary: Fetch and run/save Python scripts from GitHub.
Home-page: https://github.com/nabeelxdd/pip-nabeelxd
Author: Nabeel
Author-email: your-email@example.com
Requires-Python: >=3.6
Requires-Dist: requests
Dynamic: author
Dynamic: author-email
Dynamic: description
Dynamic: description-content-type
Dynamic: home-page
Dynamic: requires-dist
Dynamic: requires-python
Dynamic: summary
